hampst/__init__.py
hampst-3.0.0.dist-info/METADATA
hampst-3.0.0.dist-info/WHEEL
hampst-3.0.0.dist-info/RECORD
